{
    "version": "1.3.354",
    "description": "Open-source scientific and technical publishing system built on Pandoc",
    "homepage": "https://quarto.org",
    "license": "GPL-2.0-only",
    "architecture": {
        "64bit": {
            "url": "https://github.com/quarto-dev/quarto-cli/releases/download/v1.3.354/quarto-1.3.354-win.zip",
            "hash": "e0f0096af428f37b1e995cbca4b082c954734c2ddeff8c4ae14937942cacfae9"
        }
    },
    "bin": "bin\\quarto.exe",
    "checkver": {
        "github": "https://github.com/quarto-dev/quarto-cli"
    },
    "autoupdate": {
        "architecture": {
            "64bit": {
                "url": "https://github.com/quarto-dev/quarto-cli/releases/download/v$version/quarto-$version-win.zip"
            }
        },
        "hash": {
            "url": "$baseurl/quarto-$version-checksums.txt",
            "find": "$sha256\\s+$basename"
        }
    }
}
